{
  "backend": "apple-sfspeechrecognizer",
  "host": "shaws-macbook-pro.local",
  "locale": "en-US",
  "model": "unknown",
  "requiresOnDeviceRecognition": true,
  "schema": "eliza_stage_b_stt_apple_v1",
  "status": "ok",
  "supportsOnDeviceRecognition": true,
  "utteranceCount": 5,
  "utterances": [
    {
      "audioDurationSec": 1.996,
      "error": null,
      "hypothesis": "Turn on the kitchen light",
      "id": "utt-01",
      "latencyMs": 335.12306213378906,
      "realTimeFactor": 0.16789732571833119,
      "recognized": true,
      "reference": "turn on the kitchen lights"
    },
    {
      "audioDurationSec": 2.4100000000000001,
      "error": null,
      "hypothesis": "Set a reminder for tomorrow morning",
      "id": "utt-02",
      "latencyMs": 43.403029441833496,
      "realTimeFactor": 0.01800955578499315,
      "recognized": true,
      "reference": "set a reminder for tomorrow morning"
    },
    {
      "audioDurationSec": 2.0433124999999999,
      "error": null,
      "hypothesis": "What time is it in Tokyo",
      "id": "utt-03",
      "latencyMs": 39.852023124694824,
      "realTimeFactor": 0.019503635946383546,
      "recognized": true,
      "reference": "what time is it in tokyo"
    },
    {
      "audioDurationSec": 1.6366875000000001,
      "error": null,
      "hypothesis": "Open the front door",
      "id": "utt-04",
      "latencyMs": 35.627961158752441,
      "realTimeFactor": 0.021768334614123003,
      "recognized": true,
      "reference": "open the front door"
    },
    {
      "audioDurationSec": 1.9853125,
      "error": null,
      "hypothesis": "Thanks that is all for now",
      "id": "utt-05",
      "latencyMs": 38.616061210632324,
      "realTimeFactor": 0.019450872953568933,
      "recognized": true,
      "reference": "thanks that is all for now"
    }
  ]
}
